odoo10_addon_account_payment_return-10.0.1.1.0-py2.7-nspkg.pth
odoo/addons/account_payment_return/README.rst
odoo/addons/account_payment_return/__init__.py
odoo/addons/account_payment_return/__manifest__.py
odoo/addons/account_payment_return/data/ir_sequence_data.xml
odoo/addons/account_payment_return/i18n/am.po
odoo/addons/account_payment_return/i18n/ar.po
odoo/addons/account_payment_return/i18n/bg.po
odoo/addons/account_payment_return/i18n/ca.po
odoo/addons/account_payment_return/i18n/cs.po
odoo/addons/account_payment_return/i18n/de.po
odoo/addons/account_payment_return/i18n/el_GR.po
odoo/addons/account_payment_return/i18n/es.po
odoo/addons/account_payment_return/i18n/es_CR.po
odoo/addons/account_payment_return/i18n/es_EC.po
odoo/addons/account_payment_return/i18n/es_ES.po
odoo/addons/account_payment_return/i18n/es_MX.po
odoo/addons/account_payment_return/i18n/es_VE.po
odoo/addons/account_payment_return/i18n/et.po
odoo/addons/account_payment_return/i18n/fi.po
odoo/addons/account_payment_return/i18n/fr.po
odoo/addons/account_payment_return/i18n/gl.po
odoo/addons/account_payment_return/i18n/hr.po
odoo/addons/account_payment_return/i18n/hr_HR.po
odoo/addons/account_payment_return/i18n/it.po
odoo/addons/account_payment_return/i18n/lt.po
odoo/addons/account_payment_return/i18n/nl.po
odoo/addons/account_payment_return/i18n/nl_BE.po
odoo/addons/account_payment_return/i18n/pl.po
odoo/addons/account_payment_return/i18n/pt.po
odoo/addons/account_payment_return/i18n/pt_BR.po
odoo/addons/account_payment_return/i18n/pt_PT.po
odoo/addons/account_payment_return/i18n/ro.po
odoo/addons/account_payment_return/i18n/ru.po
odoo/addons/account_payment_return/i18n/sl.po
odoo/addons/account_payment_return/i18n/th.po
odoo/addons/account_payment_return/i18n/tr.po
odoo/addons/account_payment_return/i18n/vi.po
odoo/addons/account_payment_return/i18n/zh_CN.po
odoo/addons/account_payment_return/models/__init__.py
odoo10_addon_account_payment_return-10.0.1.1.0.dist-info/DESCRIPTION.rst
odoo10_addon_account_payment_return-10.0.1.1.0.dist-info/METADATA
odoo10_addon_account_payment_return-10.0.1.1.0.dist-info/RECORD
odoo10_addon_account_payment_return-10.0.1.1.0.dist-info/WHEEL
odoo10_addon_account_payment_return-10.0.1.1.0.dist-info/metadata.json
odoo10_addon_account_payment_return-10.0.1.1.0.dist-info/namespace_packages.txt
odoo10_addon_account_payment_return-10.0.1.1.0.dist-info/top_level.txt
